annotationfactory/__init__.py
annotationfactory/annotationconverter/__init__.py
annotationfactory/annotationwriter/__init__.py
annotationfactory/models/annotation.py
annotationfactory/models/region.py
annotationfactory/templates/annotation.txt
annotationfactory/templates/annotation.xml
annotationfactory/templates/schema.json
annotationfactory-0.0.1.dev304.dist-info/LICENSE
annotationfactory-0.0.1.dev304.dist-info/METADATA
annotationfactory-0.0.1.dev304.dist-info/WHEEL
annotationfactory-0.0.1.dev304.dist-info/top_level.txt
annotationfactory-0.0.1.dev304.dist-info/RECORD
