Metadata-Version: 2.1
Name: annotationfactory
Version: 0.0.1.dev304
Summary: annotation factory python sdk
Home-page: https://github.com/Microsoft/Annotation-Factory
License: MIT
Platform: UNKNOWN
Classifier: Programming Language :: Python :: 3
Classifier: Operating System :: OS Independent
Requires-Dist: jinja2
Requires-Dist: jsonschema
Requires-Dist: xmltodict
